mcp_server_fetch_python/__init__.py
mcp_server_fetch_python/server.py
mcp_server_fetch_python/settings.py
mcp_server_fetch_python-0.1.1.dist-info/METADATA
mcp_server_fetch_python-0.1.1.dist-info/WHEEL
mcp_server_fetch_python-0.1.1.dist-info/entry_points.txt
mcp_server_fetch_python-0.1.1.dist-info/licenses/LICENSE
mcp_server_fetch_python-0.1.1.dist-info/RECORD
