Metadata-Version: 2.4
Name: mcp-server-fetch-python
Version: 0.1.1
Summary: This is an MCP server that provides comprehensive tools for extracting and transforming web content into various formats, including support for JavaScript-rendered content and media files
Project-URL: Homepage, https://github.com/tatn/mcp-server-fetch-python
Project-URL: Repository, https://github.com/tatn/mcp-server-fetch-python
Author: tatn
License-Expression: MIT
License-File: LICENSE
Classifier: Development Status :: 3 - Alpha
Classifier: Intended Audience :: Developers
Classifier: License :: OSI Approved :: MIT License
Classifier: Programming Language :: Python :: 3
Classifier: Programming Language :: Python :: 3.11
Requires-Python: >=3.11
Requires-Dist: httpx>=0.28.1
Requires-Dist: markitdown>=0.1.1
Requires-Dist: mcp>=1.2.0
Requires-Dist: openai>=1.59.8
Requires-Dist: playwright>=1.49.1
Requires-Dist: pydantic-settings>=2.7.1
